fast_dag/__init__.py
fast_dag/dag.py
fast_dag/fsm.py
fast_dag/registry.py
fast_dag/runner.py
fast_dag/core/__init__.py
fast_dag/core/connections.py
fast_dag/core/context.py
fast_dag/core/exceptions.py
fast_dag/core/introspection.py
fast_dag/core/node.py
fast_dag/core/types.py
fast_dag/core/validation.py
fast_dag/visualization/__init__.py
fast_dag/visualization/base.py
fast_dag/visualization/graphviz.py
fast_dag/visualization/mermaid.py
fast_dag-0.1.0.dist-info/METADATA
fast_dag-0.1.0.dist-info/WHEEL
fast_dag-0.1.0.dist-info/licenses/LICENSE
fast_dag-0.1.0.dist-info/RECORD
