Metadata-Version: 2.4
Name: fast-dag
Version: 0.1.0
Summary: Add your description here
Author: Felix Geilert
Maintainer: Felix Geilert
License: MIT
License-File: LICENSE
Keywords: dag,workflow,workflow-engine
Classifier: Development Status :: 4 - Beta
Classifier: Intended Audience :: Developers
Classifier: License :: OSI Approved :: MIT License
Classifier: Programming Language :: Python :: 3
Classifier: Programming Language :: Python :: 3.10
Classifier: Programming Language :: Python :: 3.11
Classifier: Programming Language :: Python :: 3.12
Classifier: Programming Language :: Python :: 3.13
Classifier: Topic :: Internet :: WWW/HTTP
Classifier: Topic :: Software Development :: Libraries :: Python Modules
Requires-Python: >=3.10
Provides-Extra: all
Requires-Dist: graphviz>=0.20.0; extra == 'all'
Requires-Dist: msgspec>=0.19.0; extra == 'all'
Requires-Dist: pyyaml>=6.0; extra == 'all'
Provides-Extra: dev
Requires-Dist: mypy>=1.17.0; extra == 'dev'
Requires-Dist: pre-commit>=3.0.0; extra == 'dev'
Requires-Dist: pytest-asyncio>=0.21.0; extra == 'dev'
Requires-Dist: pytest-cov>=4.0.0; extra == 'dev'
Requires-Dist: pytest>=7.0.0; extra == 'dev'
Requires-Dist: ruff>=0.12.3; extra == 'dev'
Requires-Dist: twine>=6.1.0; extra == 'dev'
Provides-Extra: serialize
Requires-Dist: msgspec>=0.19.0; extra == 'serialize'
Requires-Dist: pyyaml>=6.0; extra == 'serialize'
Provides-Extra: viz
Requires-Dist: graphviz>=0.20.0; extra == 'viz'
